deepmini/__init__.py
deepmini/test.py
deepmini/datasets/__init__.py
deepmini/datasets/datasets.py
deepmini/utils/__init__.py
deepmini/utils/funcs.py
deepmini-0.0.5.dist-info/LICENSE
deepmini-0.0.5.dist-info/METADATA
deepmini-0.0.5.dist-info/WHEEL
deepmini-0.0.5.dist-info/top_level.txt
deepmini-0.0.5.dist-info/RECORD
